{
  "project_info": {
    "project_number": "307303768816",
    "firebase_url": "https://ecot-c5b7f-default-rtdb.asia-southeast1.firebasedatabase.app",
    "project_id": "ecot-c5b7f",
    "storage_bucket": "ecot-c5b7f.firebasestorage.app"
  },
  "client": [
    {
      "client_info": {
        "mobilesdk_app_id": "1:307303768816:android:e71d613284d31ebfb15835",
        "android_client_info": {
          "package_name": "com.example.ecotrack"
        }
      },
      "oauth_client": [],
      "api_key": [
        {
          "current_key": "AIzaSyAMIBeazJg_uzfUCwHBHyCD-i_kGlidgC8"
        }
      ],
      "services": {
        "appinvite_service": {
          "other_platform_oauth_client": []
        }
      }
    }
  ],
  "configuration_version": "1"
}